LICENSE
README.md
setup.cfg
setup.py
ccstiet/__init__.py
ccstiet/ccstiet.py
ccstiet/llama2.py
ccstiet.egg-info/PKG-INFO
ccstiet.egg-info/SOURCES.txt
ccstiet.egg-info/dependency_links.txt
ccstiet.egg-info/requires.txt
ccstiet.egg-info/top_level.txt